clio/__init__.py
clio/config.py
clio/path.py
clio/shell.py
clio/sync.py
clio/syneto_clio.py
clio/kube/__init__.py
clio/kube/container.py
clio/prerequisites/__init__.py
clio/prerequisites/giove.py
clio/prerequisites/remote_connections_utilities.py
syneto_clio-1.0.0.dist-info/LICENSE.txt
syneto_clio-1.0.0.dist-info/METADATA
syneto_clio-1.0.0.dist-info/WHEEL
syneto_clio-1.0.0.dist-info/entry_points.txt
syneto_clio-1.0.0.dist-info/top_level.txt
syneto_clio-1.0.0.dist-info/RECORD
