Metadata-Version: 2.1
Name: syneto-clio
Version: 1.0.0
Summary: "An easy to use CLI tool for running faster Kubernetes and Docker commands."
Author: "Alexandra Veres",
Author-email: "alexandra.veres@syneto.eu",
License: "MIT"
Keywords: syneto,clio
Classifier: Programming Language :: Python :: 3
Classifier: License :: OSI Approved :: MIT License
License-File: LICENSE.txt
Requires-Dist: click
